{
  "lastUpdated": "2026-01-31T12:43:53.822Z",
  "screenings": [
    {
      "title": "John Henry England Celebrates the Little Holidays and the Olympics!",
      "venue": "Avalon Theater",
      "date": "2026-01-31",
      "time": "10:30",
      "poster": null,
      "ticketLink": "https://www.theavalon.org/films/john-henry-england-celebrates-the-little-holdays/"
    },
    {
      "title": "A Private Life (2025)",
      "venue": "Avalon Theater",
      "date": "2026-01-31",
      "time": "11:15",
      "poster": "https://image.tmdb.org/t/p/w500/AnZ9XzhouSSvQH337923RPFTaqK.jpg",
      "ticketLink": "https://www.theavalon.org/films/a-private-life/"
    },
    {
      "title": "MARTY SUPREME (2025)",
      "venue": "Angelika Pop-Up at Union Market",
      "date": "2026-01-31",
      "time": "12:00",
      "poster": "https://d35zcch9f9it10.cloudfront.net/assets/images/afc/scroll_arrow_up.svg",
      "ticketLink": null
    },
    {
      "title": "ALL THAT'S LEFT OF YOU (2025)",
      "venue": "Angelika Pop-Up at Union Market",
      "date": "2026-01-31",
      "time": "12:15",
      "poster": "https://image.tmdb.org/t/p/w500/iTGzHTKpb828Gbd7mcQqCjEYd5b.jpg",
      "ticketLink": null
    },
    {
      "title": "THE VOICE OF HIND RAJAB (2025)",
      "venue": "Angelika Pop-Up at Union Market",
      "date": "2026-01-31",
      "time": "12:30",
      "poster": "https://image.tmdb.org/t/p/w500/fBcBY8kdBiPsRdtkbldwg3ThlyJ.jpg",
      "ticketLink": null
    },
    {
      "title": "Hamnet (2025)",
      "venue": "Avalon Theater",
      "date": "2026-01-31",
      "time": "13:45",
      "poster": "https://image.tmdb.org/t/p/w500/61xMzN4h8iLk0hq6oUzr9Ts6GE9.jpg",
      "ticketLink": "https://www.theavalon.org/films/hamnet/"
    },
    {
      "title": "A Private Life (2025)",
      "venue": "Avalon Theater",
      "date": "2026-01-31",
      "time": "14:00",
      "poster": "https://image.tmdb.org/t/p/w500/AnZ9XzhouSSvQH337923RPFTaqK.jpg",
      "ticketLink": "https://www.theavalon.org/films/a-private-life/"
    },
    {
      "title": "IRON LUNG (2026)",
      "venue": "Angelika Pop-Up at Union Market",
      "date": "2026-01-31",
      "time": "14:45",
      "poster": "https://image.tmdb.org/t/p/w500/7X1VkuBg2LaT7yLkj0avzGcX2VN.jpg",
      "ticketLink": null
    },
    {
      "title": "SINNERS (2025)",
      "venue": "Angelika Pop-Up at Union Market",
      "date": "2026-01-31",
      "time": "15:15",
      "poster": "https://image.tmdb.org/t/p/w500/qTvFWCGeGXgBRaINLY1zqgTPSpn.jpg",
      "ticketLink": null
    },
    {
      "title": "ALL THAT'S LEFT OF YOU (2025)",
      "venue": "Angelika Pop-Up at Union Market",
      "date": "2026-01-31",
      "time": "15:30",
      "poster": "https://image.tmdb.org/t/p/w500/iTGzHTKpb828Gbd7mcQqCjEYd5b.jpg",
      "ticketLink": null
    },
    {
      "title": "Hamnet (2025)",
      "venue": "Avalon Theater",
      "date": "2026-01-31",
      "time": "16:30",
      "poster": "https://image.tmdb.org/t/p/w500/61xMzN4h8iLk0hq6oUzr9Ts6GE9.jpg",
      "ticketLink": "https://www.theavalon.org/films/hamnet/"
    },
    {
      "title": "A Private Life (2025)",
      "venue": "Avalon Theater",
      "date": "2026-01-31",
      "time": "16:35",
      "poster": "https://image.tmdb.org/t/p/w500/AnZ9XzhouSSvQH337923RPFTaqK.jpg",
      "ticketLink": "https://www.theavalon.org/films/a-private-life/"
    },
    {
      "title": "MARTY SUPREME (2025)",
      "venue": "Angelika Pop-Up at Union Market",
      "date": "2026-01-31",
      "time": "18:30",
      "poster": "https://d35zcch9f9it10.cloudfront.net/assets/images/afc/scroll_arrow_up.svg",
      "ticketLink": null
    },
    {
      "title": "ALL THAT'S LEFT OF YOU (2025)",
      "venue": "Angelika Pop-Up at Union Market",
      "date": "2026-01-31",
      "time": "18:45",
      "poster": "https://image.tmdb.org/t/p/w500/iTGzHTKpb828Gbd7mcQqCjEYd5b.jpg",
      "ticketLink": null
    },
    {
      "title": "IRON LUNG (2026)",
      "venue": "Angelika Pop-Up at Union Market",
      "date": "2026-01-31",
      "time": "19:00",
      "poster": "https://image.tmdb.org/t/p/w500/7X1VkuBg2LaT7yLkj0avzGcX2VN.jpg",
      "ticketLink": null
    },
    {
      "title": "A Private Life (2025)",
      "venue": "Avalon Theater",
      "date": "2026-01-31",
      "time": "19:15",
      "poster": "https://image.tmdb.org/t/p/w500/AnZ9XzhouSSvQH337923RPFTaqK.jpg",
      "ticketLink": "https://www.theavalon.org/films/a-private-life/"
    },
    {
      "title": "Bugonia (2025)",
      "venue": "Avalon Theater",
      "date": "2026-01-31",
      "time": "19:30",
      "poster": "https://image.tmdb.org/t/p/w500/rSdOua3wKMEaFWDcKAYWRjXQWOt.jpg",
      "ticketLink": "https://www.theavalon.org/films/bugonia/"
    },
    {
      "title": "Before Sunset (2004)",
      "venue": "Miracle Theater",
      "date": "2026-01-31",
      "time": "20:00",
      "poster": "https://image.tmdb.org/t/p/w500/gycdE1ARByGQcK4fYR2mgpU6OO.jpg",
      "ticketLink": "https://themiracletheatre.com/events/before-sunset/"
    },
    {
      "title": "MARTY SUPREME (2025)",
      "venue": "Angelika Pop-Up at Union Market",
      "date": "2026-01-31",
      "time": "21:45",
      "poster": "https://d35zcch9f9it10.cloudfront.net/assets/images/afc/scroll_arrow_up.svg",
      "ticketLink": null
    },
    {
      "title": "IRON LUNG (2026)",
      "venue": "Angelika Pop-Up at Union Market",
      "date": "2026-01-31",
      "time": "21:55",
      "poster": "https://image.tmdb.org/t/p/w500/7X1VkuBg2LaT7yLkj0avzGcX2VN.jpg",
      "ticketLink": null
    },
    {
      "title": "ALL THAT'S LEFT OF YOU (2025)",
      "venue": "Angelika Pop-Up at Union Market",
      "date": "2026-01-31",
      "time": "22:05",
      "poster": "https://image.tmdb.org/t/p/w500/iTGzHTKpb828Gbd7mcQqCjEYd5b.jpg",
      "ticketLink": null
    },
    {
      "title": "Groundhog Day (1993)",
      "venue": "Miracle Theater",
      "date": "2026-02-01",
      "time": "14:00",
      "poster": "https://image.tmdb.org/t/p/w500/gCgt1WARPZaXnq523ySQEUKinCs.jpg",
      "ticketLink": "https://themiracletheatre.com/events/groundhog-day-4/"
    },
    {
      "title": "THERE IS NO EVIL (2020)",
      "venue": "Suns Cinema",
      "date": "2026-02-01",
      "time": "19:00",
      "poster": "https://s3.amazonaws.com/nightjarprod/content/uploads/sites/197/2026/01/23135129/AmMUP11ZWRqR08DmyigNmbG8Sit-scaled.jpg",
      "ticketLink": "https://sunscinema.com/movies/there-is-no-evil/"
    },
    {
      "title": "THE STRANGER AND THE FOG (1975)",
      "venue": "Suns Cinema",
      "date": "2026-02-01",
      "time": "19:00",
      "poster": "https://s3.amazonaws.com/nightjarprod/content/uploads/sites/197/2026/01/23135307/i35KVrJ5Qujpe1VBDsX3gLOOlI3-scaled.jpg",
      "ticketLink": "https://sunscinema.com/movies/the-stranger-and-the-fog/"
    },
    {
      "title": "GROUNDHOG DAY (1993)",
      "venue": "Suns Cinema",
      "date": "2026-02-03",
      "time": "19:00",
      "poster": "https://s3.amazonaws.com/nightjarprod/content/uploads/sites/197/2022/01/26130027/gCgt1WARPZaXnq523ySQEUKinCs.jpg",
      "ticketLink": "https://sunscinema.com/movies/groundhog-day/"
    },
    {
      "title": "FARGO (1996)",
      "venue": "Suns Cinema",
      "date": "2026-02-04",
      "time": "19:00",
      "poster": "https://s3.amazonaws.com/nightjarprod/content/uploads/sites/197/2021/11/22152106/rt7cpEr1uP6RTZykBFhBTcRaKvG-scaled.jpg",
      "ticketLink": "https://sunscinema.com/movies/fargo/"
    },
    {
      "title": "GREY GARDENS (1976)",
      "venue": "Suns Cinema",
      "date": "2026-02-05",
      "time": "19:00",
      "poster": "https://s3.amazonaws.com/nightjarprod/content/uploads/sites/197/2024/07/23165826/w4CSHmfb0veUB94gkVVNWVgjTKt.jpg",
      "ticketLink": "https://sunscinema.com/movies/grey-gardens/"
    },
    {
      "title": "THE KILLING OF A CHINESE BOOKIE (1976)",
      "venue": "Suns Cinema",
      "date": "2026-02-05",
      "time": "19:00",
      "poster": "https://s3.amazonaws.com/nightjarprod/content/uploads/sites/197/2026/01/23135835/lShPFOAbQ6y6oFYUfecmrj7BUu6-scaled.jpg",
      "ticketLink": "https://sunscinema.com/movies/the-killing-of-a-chinese-bookie/"
    },
    {
      "title": "\"Outsider. Freud\" Film Screening and Conversation with Director Yair Qedar",
      "venue": "Library of Congress",
      "date": "2026-02-05",
      "time": "19:00",
      "poster": "https://www.loc.gov/static/managed-content/uploads/sites/9/2025/12/Freud-poster-English-Small-600x600-1-250x250.jpg#250x250",
      "ticketLink": "https://www.loc.gov/item/event-419750/outsider-freud-film-screening-and-conversation-with-director-yair-qedar/2026-02-05/"
    },
    {
      "title": "FORCE MAJEURE",
      "venue": "Suns Cinema",
      "date": "2026-02-06",
      "time": "19:00",
      "poster": "https://s3.amazonaws.com/nightjarprod/content/uploads/sites/197/2026/01/23140053/41agNfzepz2DTdgTBX1fX0QclHp.jpg",
      "ticketLink": "https://sunscinema.com/movies/force-majeure-2/"
    },
    {
      "title": "THE THING (1982)",
      "venue": "Suns Cinema",
      "date": "2026-02-06",
      "time": "19:00",
      "poster": "https://s3.amazonaws.com/nightjarprod/content/uploads/sites/197/2021/11/22152044/tzGY49kseSE9QAKk47uuDGwnSCu.jpg",
      "ticketLink": "https://sunscinema.com/movies/the-thing/"
    },
    {
      "title": "DR. STRANGELOVE OR: HOW I LEARNED TO STOP WORRYING AND LOVE THE BOMB (1964)",
      "venue": "Suns Cinema",
      "date": "2026-02-07",
      "time": "19:00",
      "poster": "https://s3.amazonaws.com/nightjarprod/content/uploads/sites/197/2024/06/21112949/7SixLzxcqezkZEYU8pcHZgbkmjp.jpg",
      "ticketLink": "https://sunscinema.com/movies/dr-strangelove-or-how-i-learned-to-stop-worrying-and-love-the-bomb/"
    },
    {
      "title": "BARRY LYNDON (1975)",
      "venue": "Suns Cinema",
      "date": "2026-02-07",
      "time": "19:00",
      "poster": "https://s3.amazonaws.com/nightjarprod/content/uploads/sites/197/2026/01/23140244/A0byHUHMwZ7dtBQtfZ44QIgDbjo.jpg",
      "ticketLink": "https://sunscinema.com/movies/barry-lyndon/"
    },
    {
      "title": "When Harry Met Sally (1989)",
      "venue": "Miracle Theater",
      "date": "2026-02-07",
      "time": "19:00",
      "poster": "https://image.tmdb.org/t/p/w500/rFOiFUhTMtDetqCGClC9PIgnC1P.jpg",
      "ticketLink": "https://themiracletheatre.com/events/when-harry-met-sally-2/"
    },
    {
      "title": "When Harry Met Sally (1989)",
      "venue": "Miracle Theater",
      "date": "2026-02-08",
      "time": "14:00",
      "poster": "https://image.tmdb.org/t/p/w500/rFOiFUhTMtDetqCGClC9PIgnC1P.jpg",
      "ticketLink": "https://themiracletheatre.com/events/when-harry-met-sally-3/"
    },
    {
      "title": "Still We Rise (2022)",
      "venue": "National Gallery of Art",
      "date": "2026-02-08",
      "time": "14:00",
      "poster": "https://image.tmdb.org/t/p/w500/zjenVykckQU7lycQIk3Ag1P8kTZ.jpg",
      "ticketLink": "https://www.nga.gov/calendar?type%5B103026%5D=103026"
    },
    {
      "title": "LAW OF THE BORDER (1966)",
      "venue": "Suns Cinema",
      "date": "2026-02-08",
      "time": "19:00",
      "poster": "https://s3.amazonaws.com/nightjarprod/content/uploads/sites/197/2026/01/23140644/bGpWiiHLH1ji1lRWC4kIXAZ2b3O.jpg",
      "ticketLink": "https://sunscinema.com/movies/law-of-the-border/"
    },
    {
      "title": "CHRONICLE OF THE YEARS OF FIRE (1975)",
      "venue": "Suns Cinema",
      "date": "2026-02-08",
      "time": "19:00",
      "poster": "https://s3.amazonaws.com/nightjarprod/content/uploads/sites/197/2026/01/23140537/wtx3qqdwwp3sNANYfAFXl5tKZE6.jpg",
      "ticketLink": "https://sunscinema.com/movies/chronicle-of-the-years-of-fire/"
    },
    {
      "title": "LE SILENCE DE LA MER (1949)",
      "venue": "Suns Cinema",
      "date": "2026-02-10",
      "time": "19:00",
      "poster": "https://s3.amazonaws.com/nightjarprod/content/uploads/sites/197/2026/01/23140831/5yagil6aUFTkdYqIoldZmDAGpay.jpg",
      "ticketLink": "https://sunscinema.com/movies/le-silence-de-la-mer/"
    },
    {
      "title": "ARMY OF SHADOWS (1969)",
      "venue": "Suns Cinema",
      "date": "2026-02-10",
      "time": "19:00",
      "poster": "https://s3.amazonaws.com/nightjarprod/content/uploads/sites/197/2026/01/23141105/aqNZWM9bspt8zaDvVRIRiWxRVJ7.jpg",
      "ticketLink": "https://sunscinema.com/movies/army-of-shadows/"
    },
    {
      "title": "PASSPORT TO DESTINY (1944)",
      "venue": "Suns Cinema",
      "date": "2026-02-11",
      "time": "19:00",
      "poster": "https://s3.amazonaws.com/nightjarprod/content/uploads/sites/197/2026/01/27121654/kbTBreDPUUQSjvQdWDAst8vqpjD.jpg",
      "ticketLink": "https://sunscinema.com/movies/passport-to-destiny/"
    },
    {
      "title": "THE GREAT DICTATOR (1940)",
      "venue": "Suns Cinema",
      "date": "2026-02-11",
      "time": "19:00",
      "poster": "https://s3.amazonaws.com/nightjarprod/content/uploads/sites/197/2026/01/25111821/1QpO9wo7JWecZ4NiBuu625FiY1j.jpg",
      "ticketLink": "https://sunscinema.com/movies/the-great-dictator/"
    },
    {
      "title": "THE GREAT SILENCE (1968)",
      "venue": "Suns Cinema",
      "date": "2026-02-12",
      "time": "19:00",
      "poster": "https://s3.amazonaws.com/nightjarprod/content/uploads/sites/197/2026/01/25112156/3kpxS7SZMyYSXvhDnmxQXOOxiTM-1-scaled.jpg",
      "ticketLink": "https://sunscinema.com/movies/the-great-silence/"
    },
    {
      "title": "MCCABE & MRS. MILLER (1971)",
      "venue": "Suns Cinema",
      "date": "2026-02-12",
      "time": "19:00",
      "poster": "https://s3.amazonaws.com/nightjarprod/content/uploads/sites/197/2026/01/25112425/eQ9hDaTNpZ4wb7FWdqoJcOCJBve-scaled.jpg",
      "ticketLink": "https://sunscinema.com/movies/mccabe-mrs-miller/"
    },
    {
      "title": "Film screening: Flamingo Road (1949)",
      "venue": "Library of Congress",
      "date": "2026-02-12",
      "time": "19:00",
      "poster": "https://www.loc.gov/static/managed-content/uploads/sites/9/2025/08/Flamingo-Road-357x500.jpg#357x500",
      "ticketLink": "https://www.loc.gov/item/event-419946/film-screening-flamingo-road-1949/2026-02-12/"
    },
    {
      "title": "BARRY LYNDON (1975)",
      "venue": "Suns Cinema",
      "date": "2026-02-13",
      "time": "19:00",
      "poster": "https://s3.amazonaws.com/nightjarprod/content/uploads/sites/197/2026/01/23140244/A0byHUHMwZ7dtBQtfZ44QIgDbjo.jpg",
      "ticketLink": "https://sunscinema.com/movies/barry-lyndon/"
    },
    {
      "title": "AMÉLIE (2001)",
      "venue": "Suns Cinema",
      "date": "2026-02-13",
      "time": "19:00",
      "poster": "https://s3.amazonaws.com/nightjarprod/content/uploads/sites/197/2024/03/22100645/nSxDa3M9aMvGVLoItzWTepQ5h5d-scaled.jpg",
      "ticketLink": "https://sunscinema.com/movies/amelie/"
    },
    {
      "title": "Casablanca (1943)",
      "venue": "National Gallery of Art",
      "date": "2026-02-14",
      "time": "14:00",
      "poster": "https://image.tmdb.org/t/p/w500/lGCEKlJo2CnWydQj7aamY7s1S7Q.jpg",
      "ticketLink": "https://www.nga.gov/calendar?type%5B103026%5D=103026"
    },
    {
      "title": "Lady and the Tramp (1955)",
      "venue": "Miracle Theater",
      "date": "2026-02-14",
      "time": "16:00",
      "poster": "https://image.tmdb.org/t/p/w500/340NcWz9SQXWQyf4oicMxjbrLOb.jpg",
      "ticketLink": "https://themiracletheatre.com/events/lady-and-the-tramp-3/"
    },
    {
      "title": "METROSEXUAL: DANCE PARTY",
      "venue": "Suns Cinema",
      "date": "2026-02-14",
      "time": "19:00",
      "poster": "https://s3.amazonaws.com/nightjarprod/content/uploads/sites/197/2026/01/26130410/metrosexual-vday-flyer-2.jpeg",
      "ticketLink": "https://sunscinema.com/special_events/metrosexual-dance-party-2/"
    },
    {
      "title": "An Affair to Remember (1957)",
      "venue": "Miracle Theater",
      "date": "2026-02-14",
      "time": "19:00",
      "poster": "https://image.tmdb.org/t/p/w500/jwbWglYHbjqUu8M9DjTYzTOFklt.jpg",
      "ticketLink": "https://themiracletheatre.com/events/an-affair-to-remember-2/"
    },
    {
      "title": "Sunset Boulevard (1950)",
      "venue": "National Gallery of Art",
      "date": "2026-02-15",
      "time": "14:00",
      "poster": "https://image.tmdb.org/t/p/w500/zt8aQ6ksqK6p1AopC5zVTDS9pKT.jpg",
      "ticketLink": "https://www.nga.gov/calendar?type%5B103026%5D=103026"
    },
    {
      "title": "HAPPY TOGETHER (1997)",
      "venue": "Suns Cinema",
      "date": "2026-02-17",
      "time": "19:00",
      "poster": "https://image.tmdb.org/t/p/w500/kO4KjUkQOfWSBw06Bdl7m6AlEP7.jpg",
      "ticketLink": "https://sunscinema.com/movies/happy-together/"
    },
    {
      "title": "MOONLIGHT (2016)",
      "venue": "Suns Cinema",
      "date": "2026-02-17",
      "time": "19:00",
      "poster": "https://s3.amazonaws.com/nightjarprod/content/uploads/sites/197/2023/01/26161934/4911T5FbJ9eD2Faz5Z8cT3SUhU3-scaled.jpg",
      "ticketLink": "https://sunscinema.com/movies/moonlight/"
    },
    {
      "title": "DAMNATION (2014)",
      "venue": "Suns Cinema",
      "date": "2026-02-18",
      "time": "19:00",
      "poster": "https://s3.amazonaws.com/nightjarprod/content/uploads/sites/197/2023/05/02110514/iW1WHmZEk9QTeY4qp7gjaDcCPDS.jpg",
      "ticketLink": "https://sunscinema.com/movies/damnation/"
    },
    {
      "title": "WERCKMEISTER HARMONIES (2001)",
      "venue": "Suns Cinema",
      "date": "2026-02-18",
      "time": "19:00",
      "poster": "https://s3.amazonaws.com/nightjarprod/content/uploads/sites/197/2026/01/25113301/fzG0xks6HNSnQg6atlF98brHvIT-scaled.jpg",
      "ticketLink": "https://sunscinema.com/movies/werckmeister-harmonies/"
    },
    {
      "title": "COMPENSATION (1999)",
      "venue": "Suns Cinema",
      "date": "2026-02-19",
      "time": "19:00",
      "poster": "https://s3.amazonaws.com/nightjarprod/content/uploads/sites/197/2026/01/25113502/k2SXL3KcW0PEjl8SC6mZoBuNPul.jpg",
      "ticketLink": "https://sunscinema.com/movies/compensation/"
    },
    {
      "title": "LOSING GROUND (1982)",
      "venue": "Suns Cinema",
      "date": "2026-02-19",
      "time": "19:00",
      "poster": "https://s3.amazonaws.com/nightjarprod/content/uploads/sites/197/2022/12/21140223/zSZT7ndjNUsskQq9IWosW3a9cbk.jpg",
      "ticketLink": "https://sunscinema.com/movies/losing-ground/"
    },
    {
      "title": "MARKETA LAZAROVÁ (1967)",
      "venue": "Suns Cinema",
      "date": "2026-02-20",
      "time": "19:00",
      "poster": "https://s3.amazonaws.com/nightjarprod/content/uploads/sites/197/2026/01/25113929/c16ArEPUqb0RdUyZBH6fnO7ZiLL.jpg",
      "ticketLink": "https://sunscinema.com/movies/marketa-lazarova/"
    },
    {
      "title": "BOTTLE ROCKET (1993)",
      "venue": "Suns Cinema",
      "date": "2026-02-20",
      "time": "19:00",
      "poster": "https://s3.amazonaws.com/nightjarprod/content/uploads/sites/197/2026/01/25114234/wOPiNYt9V3Cbr9Izeddwj7nU8RT.jpg",
      "ticketLink": "https://sunscinema.com/movies/bottle-rocket/"
    },
    {
      "title": "The General (1926)",
      "venue": "National Gallery of Art",
      "date": "2026-02-21",
      "time": "14:00",
      "poster": "https://image.tmdb.org/t/p/w500/nIp4gIXogCjfB1QABNsWwa9gSca.jpg",
      "ticketLink": "https://www.nga.gov/calendar?type%5B103026%5D=103026"
    },
    {
      "title": "HAIL THE NEW PURITAN (1986)",
      "venue": "Suns Cinema",
      "date": "2026-02-21",
      "time": "19:00",
      "poster": "https://s3.amazonaws.com/nightjarprod/content/uploads/sites/197/2026/01/28110252/riscm3ibZai3JIOrAKc7fQFqItr-scaled.jpg",
      "ticketLink": "https://sunscinema.com/movies/hail-the-new-puritan/"
    },
    {
      "title": "NADJA (1995)",
      "venue": "Suns Cinema",
      "date": "2026-02-21",
      "time": "19:00",
      "poster": "https://s3.amazonaws.com/nightjarprod/content/uploads/sites/197/2023/09/25115311/NADJA-Poster.jpeg",
      "ticketLink": "https://sunscinema.com/movies/nadja/"
    },
    {
      "title": "Mr. Smith Goes to Washington (1939)",
      "venue": "National Gallery of Art",
      "date": "2026-02-22",
      "time": "14:00",
      "poster": "https://image.tmdb.org/t/p/w500/nDjg1fbNyq15excNDl3acd2IqAk.jpg",
      "ticketLink": "https://www.nga.gov/calendar?type%5B103026%5D=103026"
    },
    {
      "title": "CASTRATION MOVIE ANTHOLOGY i & ii",
      "venue": "Suns Cinema",
      "date": "2026-02-22",
      "time": "19:00",
      "poster": "https://s3.amazonaws.com/nightjarprod/content/uploads/sites/197/2026/01/30130530/fuEOWhlPl2INV6pNSMVr6uZdy0l-scaled.jpg",
      "ticketLink": "https://sunscinema.com/movies/castration-movie-anthology-i-and-ii/"
    },
    {
      "title": "NITRATE KISSES (1992)",
      "venue": "Suns Cinema",
      "date": "2026-02-24",
      "time": "19:00",
      "poster": "https://s3.amazonaws.com/nightjarprod/content/uploads/sites/197/2026/01/28112559/z5dy2LpDzKLYqKN3HCf3X4XZMW3-scaled.jpg",
      "ticketLink": "https://sunscinema.com/movies/nitrate-kisses/"
    },
    {
      "title": "CLOUDBURST (1951)",
      "venue": "Suns Cinema",
      "date": "2026-02-24",
      "time": "19:00",
      "poster": "https://s3.amazonaws.com/nightjarprod/content/uploads/sites/197/2026/01/28113657/x4vlDX1xc0ZPRYnzyiGMpUOBSPv.jpg",
      "ticketLink": "https://sunscinema.com/movies/cloudburst/"
    },
    {
      "title": "NADJA (1995)",
      "venue": "Suns Cinema",
      "date": "2026-02-25",
      "time": "19:00",
      "poster": "https://s3.amazonaws.com/nightjarprod/content/uploads/sites/197/2023/09/25115311/NADJA-Poster.jpeg",
      "ticketLink": "https://sunscinema.com/movies/nadja/"
    },
    {
      "title": "THE TURIN HORSE (2011)",
      "venue": "Suns Cinema",
      "date": "2026-02-25",
      "time": "19:00",
      "poster": "https://s3.amazonaws.com/nightjarprod/content/uploads/sites/197/2026/01/25115614/2kSElneXSKmMsGL55k0CbPGqLbu1.jpg",
      "ticketLink": "https://sunscinema.com/movies/the-turin-horse/"
    },
    {
      "title": "WOLF’S HOLE (1987)",
      "venue": "Suns Cinema",
      "date": "2026-02-26",
      "time": "19:00",
      "poster": "https://s3.amazonaws.com/nightjarprod/content/uploads/sites/197/2026/01/25115805/1GfaK7FUqgc90peUBH4uSWIVCAr.jpg",
      "ticketLink": "https://sunscinema.com/movies/wolfs-hole/"
    },
    {
      "title": "DEAD MOUNTAINEER’S HOTEL (1979)",
      "venue": "Suns Cinema",
      "date": "2026-02-26",
      "time": "19:00",
      "poster": "https://s3.amazonaws.com/nightjarprod/content/uploads/sites/197/2026/01/27121412/6zD8cZ7gTvNLJdjEcnllYyJjkMY.jpg",
      "ticketLink": "https://sunscinema.com/movies/dead-mountaineers-hotel/"
    },
    {
      "title": "THE ASCENT (2019)",
      "venue": "Suns Cinema",
      "date": "2026-02-27",
      "time": "19:00",
      "poster": "https://s3.amazonaws.com/nightjarprod/content/uploads/sites/197/2023/11/10141814/nbGyTnH1TREKgZXLxEJNnDVohYC.jpg",
      "ticketLink": "https://sunscinema.com/movies/the-ascent/"
    },
    {
      "title": "ANDREI RUBLEV (1966)",
      "venue": "Suns Cinema",
      "date": "2026-02-27",
      "time": "19:00",
      "poster": "https://s3.amazonaws.com/nightjarprod/content/uploads/sites/197/2026/01/25120130/910xRIUmNJrWH2hkQifBJtoPp5R.jpg",
      "ticketLink": "https://sunscinema.com/movies/andrei-rublev/"
    },
    {
      "title": "WOLF’S HOLE (1987)",
      "venue": "Suns Cinema",
      "date": "2026-02-28",
      "time": "19:00",
      "poster": "https://s3.amazonaws.com/nightjarprod/content/uploads/sites/197/2026/01/25115805/1GfaK7FUqgc90peUBH4uSWIVCAr.jpg",
      "ticketLink": "https://sunscinema.com/movies/wolfs-hole/"
    },
    {
      "title": "DEAD MOUNTAINEER’S HOTEL (1979)",
      "venue": "Suns Cinema",
      "date": "2026-02-28",
      "time": "19:00",
      "poster": "https://s3.amazonaws.com/nightjarprod/content/uploads/sites/197/2026/01/27121412/6zD8cZ7gTvNLJdjEcnllYyJjkMY.jpg",
      "ticketLink": "https://sunscinema.com/movies/dead-mountaineers-hotel/"
    }
  ]
}